FlaskDeferredHandler.py
setup.py
FlaskDeferredHandler.egg-info/PKG-INFO
FlaskDeferredHandler.egg-info/SOURCES.txt
FlaskDeferredHandler.egg-info/dependency_links.txt
FlaskDeferredHandler.egg-info/requires.txt
FlaskDeferredHandler.egg-info/top_level.txt