Metadata-Version: 1.0
Name: FlaskDeferredHandler
Version: 0.1
Summary: A Flask handler for the Google Appengine's deferred library
Home-page: http://github.com/kaste/FlaskDeferredHandler
Author: herr kaste
Author-email: herr.kaste@gmail.com
License: BSD
Keywords: flask google appengine gae deferred
Platform: UNKNOWN
Classifier: Development Status :: 4 - Beta
Classifier: Environment :: Web Environment
Classifier: Intended Audience :: Developers
Classifier: License :: OSI Approved :: BSD License
Classifier: Operating System :: OS Independent
Classifier: Programming Language :: Python
Classifier: Topic :: Internet :: WWW/HTTP
Classifier: Topic :: Software Development :: Libraries
